metamart_managed_apis/__init__.py
metamart_managed_apis/plugin.py
metamart_managed_apis/api/__init__.py
metamart_managed_apis/api/apis_metadata.py
metamart_managed_apis/api/app.py
metamart_managed_apis/api/config.py
metamart_managed_apis/api/error_handlers.py
metamart_managed_apis/api/response.py
metamart_managed_apis/api/utils.py
metamart_managed_apis/api/routes/__init__.py
metamart_managed_apis/api/routes/delete.py
metamart_managed_apis/api/routes/deploy.py
metamart_managed_apis/api/routes/disable.py
metamart_managed_apis/api/routes/enable.py
metamart_managed_apis/api/routes/health.py
metamart_managed_apis/api/routes/health_auth.py
metamart_managed_apis/api/routes/ip.py
metamart_managed_apis/api/routes/kill.py
metamart_managed_apis/api/routes/last_dag_logs.py
metamart_managed_apis/api/routes/run_automation.py
metamart_managed_apis/api/routes/status.py
metamart_managed_apis/api/routes/trigger.py
metamart_managed_apis/operations/__init__.py
metamart_managed_apis/operations/delete.py
metamart_managed_apis/operations/deploy.py
metamart_managed_apis/operations/health.py
metamart_managed_apis/operations/kill_all.py
metamart_managed_apis/operations/last_dag_logs.py
metamart_managed_apis/operations/state.py
metamart_managed_apis/operations/status.py
metamart_managed_apis/operations/trigger.py
metamart_managed_apis/resources/__init__.py
metamart_managed_apis/resources/dag_runner.j2
metamart_managed_apis/utils/__init__.py
metamart_managed_apis/utils/logger.py
metamart_managed_apis/utils/parser.py
metamart_managed_apis/views/__init__.py
metamart_managed_apis/views/rest_api.py
metamart_managed_apis/views/templates/rest_api/index.html
metamart_managed_apis/workflows/__init__.py
metamart_managed_apis/workflows/config.py
metamart_managed_apis/workflows/workflow_builder.py
metamart_managed_apis/workflows/workflow_factory.py
metamart_managed_apis/workflows/ingestion/__init__.py
metamart_managed_apis/workflows/ingestion/application.py
metamart_managed_apis-1.6.0.0.dev0.dist-info/LICENSE
metamart_managed_apis-1.6.0.0.dev0.dist-info/METADATA
metamart_managed_apis-1.6.0.0.dev0.dist-info/WHEEL
metamart_managed_apis-1.6.0.0.dev0.dist-info/entry_points.txt
metamart_managed_apis-1.6.0.0.dev0.dist-info/top_level.txt
metamart_managed_apis-1.6.0.0.dev0.dist-info/RECORD
