Metadata-Version: 2.1
Name: metamart_managed_apis
Version: 1.6.0.0.dev0
Summary: Airflow REST APIs to create and manage DAGS
Author: MetaMart Committers
License: Apache License
Project-URL: Homepage, https://meta-mart.org/
Project-URL: Documentation, https://docs.meta-mart.org/
Project-URL: Source, https://github.com/meta-mart/MetaMart
Requires-Python: >=3.8
License-File: LICENSE
Requires-Dist: pendulum ~=3.0
Requires-Dist: apache-airflow >=2.2.2
Requires-Dist: Flask ==2.2.5
Requires-Dist: Flask-Admin ==1.6.0
Provides-Extra: dev
Requires-Dist: black ==22.3.0 ; extra == 'dev'
Requires-Dist: pytest ; extra == 'dev'
Requires-Dist: pylint ; extra == 'dev'
Requires-Dist: pytest-cov ; extra == 'dev'
Requires-Dist: isort ; extra == 'dev'
Requires-Dist: pycln ; extra == 'dev'
